AGonR.v
// Rainer D. Gonzaga S08
`timescale 1ns / 1ps

module odd_up_down_counter (Y, reset, clock, count);

    input Y, reset, clock;
    output reg [3:0] count;

    initial begin
        $display("Rainer D. Gonzaga");
        $display("Behavioral odd up-down Binary counter using D Flip Flop");
    end

    always @(posedge clock, negedge reset) begin
        if (reset == 1'b0) begin
            count <= 4'b0001; 
        end else begin
            case (count)
                4'b0001: count <= (Y) ? 4'b0011 : 4'b1111;
                4'b0011: count <= (Y) ? 4'b0101 : 4'b0001;
                4'b0101: count <= (Y) ? 4'b0111 : 4'b0011;
                4'b0111: count <= (Y) ? 4'b1001 : 4'b0101;
                4'b1001: count <= (Y) ? 4'b1011 : 4'b0111;
                4'b1011: count <= (Y) ? 4'b1101 : 4'b1001;
                4'b1101: count <= (Y) ? 4'b1111 : 4'b1011;
                4'b1111: count <= (Y) ? 4'b0001 : 4'b1101;
                default: count <= 4'b0001;
            endcase
        end
    end

endmodule

AGonR_tb.v
// Rainer D. Gonzaga S08
`timescale 1ns / 1ps

module odd_up_down_counter_tb;
    reg Y;
    reg reset;
    reg clock;
    wire [3:0] count;

    odd_up_down_counter uut(Y, reset, clock, count);

    initial
    begin
        clock = 1'b0;
        forever #5 clock = ~clock;
    end

    initial
    begin
        reset = 1'b0;
        #10 reset = 1'b1;
    end

    initial
    begin
        Y = 1'b0;
        #180 Y = 1'b1;
    end

    initial
    begin
        $display("Rainer D. Gonzaga, Behavioral odd up-down Binary counter using D Flip Flop");
        $monitor("time = %3d | clk = %b | rst = %b | Y = %b | count = %b", $time, clock, reset, Y, count);
        $dumpfile("AGonR.vcd");
        $dumpvars(0, odd_up_down_counter_tb);
    end

    initial #380 $finish;
endmodule

AGonR.vcd
$date
	Mon Apr 06 23:12:11 2026
$end
$version
	Icarus Verilog
$end
$timescale
	1ps
$end
$scope module odd_up_down_counter_tb $end
$var wire 4 ! count [3:0] $end
$var reg 1 " Y $end
$var reg 1 # clock $end
$var reg 1 $ reset $end
$scope module uut $end
$var wire 1 " Y $end
$var wire 1 # clock $end
$var wire 1 $ reset $end
$var reg 4 % count [3:0] $end
$upscope $end
$upscope $end
$enddefinitions $end
$comment Show the parameter values. $end
$dumpall
$end
#0
$dumpvars
b1 %
0$
0#
0"
b1 !
$end
#5000
1#
#10000
0#
1$
#15000
b1111 !
b1111 %
1#
#20000
0#
#25000
b1101 !
b1101 %
1#
#30000
0#
#35000
b1011 !
b1011 %
1#
#40000
0#
#45000
b1001 !
b1001 %
1#
#50000
0#
#55000
b111 !
b111 %
1#
#60000
0#
#65000
b101 !
b101 %
1#
#70000
0#
#75000
b11 !
b11 %
1#
#80000
0#
#85000
b1 !
b1 %
1#
#90000
0#
#95000
b1111 !
b1111 %
1#
#100000
0#
#105000
b1101 !
b1101 %
1#
#110000
0#
#115000
b1011 !
b1011 %
1#
#120000
0#
#125000
b1001 !
b1001 %
1#
#130000
0#
#135000
b111 !
b111 %
1#
#140000
0#
#145000
b101 !
b101 %
1#
#150000
0#
#155000
b11 !
b11 %
1#
#160000
0#
#165000
b1 !
b1 %
1#
#170000
0#
#175000
b1111 !
b1111 %
1#
#180000
0#
1"
#185000
b1 !
b1 %
1#
#190000
0#
#195000
b11 !
b11 %
1#
#200000
0#
#205000
b101 !
b101 %
1#
#210000
0#
#215000
b111 !
b111 %
1#
#220000
0#
#225000
b1001 !
b1001 %
1#
#230000
0#
#235000
b1011 !
b1011 %
1#
#240000
0#
#245000
b1101 !
b1101 %
1#
#250000
0#
#255000
b1111 !
b1111 %
1#
#260000
0#
#265000
b1 !
b1 %
1#
#270000
0#
#275000
b11 !
b11 %
1#
#280000
0#
#285000
b101 !
b101 %
1#
#290000
0#
#295000
b111 !
b111 %
1#
#300000
0#
#305000
b1001 !
b1001 %
1#
#310000
0#
#315000
b1011 !
b1011 %
1#
#320000
0#
#325000
b1101 !
b1101 %
1#
#330000
0#
#335000
b1111 !
b1111 %
1#
#340000
0#
#345000
b1 !
b1 %
1#
#350000
0#
#355000
b11 !
b11 %
1#
#360000
0#
#365000
b101 !
b101 %
1#
#370000
0#
#375000
b111 !
b111 %
1#
